{
  "players": [
    {
      "name": "Abe",
      "birth_date": "2018-01-01",
      "team_id": 12
    },
    {
      "name": "Boy",
      "birth_date": "2018-01-01",
      "team_id": 12
    },
    {
      "name": "Daan",
      "birth_date": "2018-01-01",
      "team_id": 12
    },
    {
      "name": "Doke",
      "birth_date": "2018-01-01",
      "team_id": 12
    },
    {
      "name": "Dylan",
      "birth_date": "2018-01-01",
      "team_id": 12
    },
    {
      "name": "Fabian",
      "birth_date": "2018-01-01",
      "team_id": 12
    },
    {
      "name": "Frank",
      "birth_date": "2018-01-01",
      "team_id": 12
    },
    {
      "name": "Gijs",
      "birth_date": "2018-01-01",
      "team_id": 12
    },
    {
      "name": "IJsbrand",
      "birth_date": "2018-01-01",
      "team_id": 12
    },
    {
      "name": "Jorrit",
      "birth_date": "2018-01-01",
      "team_id": 12
    },
    {
      "name": "Joppe",
      "birth_date": "2018-01-01",
      "team_id": 12
    },
    {
      "name": "Kevin",
      "birth_date": "2018-01-01",
      "team_id": 12
    },
    {
      "name": "Martin",
      "birth_date": "2018-01-01",
      "team_id": 12
    },
    {
      "name": "Mick",
      "birth_date": "2018-01-01",
      "team_id": 12
    },
    {
      "name": "Mitchell",
      "birth_date": "2018-01-01",
      "team_id": 12
    },
    {
      "name": "Mo",
      "birth_date": "2018-01-01",
      "team_id": 12
    },
    {
      "name": "Niekus",
      "birth_date": "2018-01-01",
      "team_id": 12
    },
    {
      "name": "Pelle",
      "birth_date": "2018-01-01",
      "team_id": 12
    },
    {
      "name": "Rik",
      "birth_date": "2018-01-01",
      "team_id": 12
    },
    {
      "name": "Tom",
      "birth_date": "2018-01-01",
      "team_id": 12
    },
    {
      "name": "Demo1",
      "birth_date": "2018-01-01",
      "team_id": 1
    },
    {
      "name": "Demo2",
      "birth_date": "2018-01-01",
      "team_id": 1
    },
    {
      "name": "Demo3",
      "birth_date": "2018-01-01",
      "team_id": 1
    }
  ]
}